CHANGELOG.md
CONTRIBUTING.md
LICENSE
MANIFEST.in
README.md
requirements-core.txt
requirements-dev.txt
requirements-doc.txt
requirements-gui.txt
requirements-opt.txt
requirements-sql.txt
requirements.txt
setup.cfg
setup.py
Bis_Miner.egg-info/PKG-INFO
Bis_Miner.egg-info/SOURCES.txt
Bis_Miner.egg-info/dependency_links.txt
Bis_Miner.egg-info/entry_points.txt
Bis_Miner.egg-info/not-zip-safe
Bis_Miner.egg-info/requires.txt
Bis_Miner.egg-info/top_level.txt
Orange/__init__.py
Orange/base.py
Orange/setup.py
Orange/tree.py
Orange/util.py
Orange/version.py
Orange/canvas/__init__.py
Orange/canvas/__main__.py
Orange/canvas/config.py
Orange/canvas/resources.py
Orange/canvas/application/__init__.py
Orange/canvas/application/aboutdialog.py
Orange/canvas/application/addons.py
Orange/canvas/application/application.py
Orange/canvas/application/canvasmain.py
Orange/canvas/application/canvastooldock.py
Orange/canvas/application/errorreporting.py
Orange/canvas/application/outputview.py
Orange/canvas/application/schemeinfo.py
Orange/canvas/application/settings.py
Orange/canvas/application/welcomedialog.py
Orange/canvas/application/widgettoolbox.py
Orange/canvas/application/tests/__init__.py
Orange/canvas/application/tests/test_addons.py
Orange/canvas/application/tests/test_canvastooldock.py
Orange/canvas/application/tests/test_outputview.py
Orange/canvas/application/tests/test_schemeinfo.py
Orange/canvas/application/tests/test_settings.py
Orange/canvas/application/tests/test_welcomedialog.py
Orange/canvas/application/tests/test_widgettoolbox.py
Orange/canvas/application/workflows/110-file-and-data-table-widget.ows
Orange/canvas/application/workflows/120-scatterplot-data-table.ows
Orange/canvas/application/workflows/130-scatterplot-visualize-subset.ows
Orange/canvas/application/workflows/250-tree-scatterplot.ows
Orange/canvas/application/workflows/305-pca.ows
Orange/canvas/application/workflows/310-clustering.ows
Orange/canvas/application/workflows/410-feature-ranking.ows
Orange/canvas/application/workflows/450-cross-validation.ows
Orange/canvas/application/workflows/470-misclassification-scatterplot.ows
Orange/canvas/application/workflows/__init__.py
Orange/canvas/canvas/__init__.py
Orange/canvas/canvas/layout.py
